{
  "chapters": [
    {
      "id": 0,
      "chapterTitle": "Multiplication Facts",
      "sections": [
        {
          "sectionTitle": "Multiplication by 2 (in order)",
          "id": 0,
          "problemIDs": [
            0,
            1,
            2,
            3,
            4,
            5,
            6,
            7,
            8
          ]
        }
      ]
    }
  ],
  "problems": [
    {
      "id": 0,
      "formulaNumbers": [
        2,
        1
      ],
      "hint": "This means something like 1 piles of 2 cookies.",
      "answer": 2,
      "formulaOperation": "multiplication",
      "formulaOrientation": "vertical",
      "type": "number"
    },
    {
      "id": 1,
      "formulaNumbers": [
        2,
        2
      ],
      "hint": "This means something like 2 piles of 2 cookies.",
      "answer": 4,
      "formulaOperation": "multiplication",
      "formulaOrientation": "vertical",
      "type": "number"
    },
    {
      "id": 2,
      "formulaNumbers": [
        2,
        3
      ],
      "hint": "This means something like 3 piles of 2 cookies.",
      "answer": 6,
      "formulaOperation": "multiplication",
      "formulaOrientation": "vertical",
      "type": "number"
    },
    {
      "id": 3,
      "formulaNumbers": [
        2,
        4
      ],
      "hint": "This means something like 4 piles of 2 cookies.",
      "answer": 8,
      "formulaOperation": "multiplication",
      "formulaOrientation": "vertical",
      "type": "number"
    },
    {
      "id": 4,
      "formulaNumbers": [
        2,
        5
      ],
      "hint": "This means something like 5 piles of 2 cookies.",
      "answer": 10,
      "formulaOperation": "multiplication",
      "formulaOrientation": "vertical",
      "type": "number"
    },
    {
      "id": 5,
      "formulaNumbers": [
        2,
        6
      ],
      "hint": "This means something like 6 piles of 2 cookies.",
      "answer": 12,
      "formulaOperation": "multiplication",
      "formulaOrientation": "vertical",
      "type": "number"
    },
    {
      "id": 6,
      "formulaNumbers": [
        2,
        7
      ],
      "hint": "This means something like 7 piles of 2 cookies.",
      "answer": 14,
      "formulaOperation": "multiplication",
      "formulaOrientation": "vertical",
      "type": "number"
    },
    {
      "id": 7,
      "formulaNumbers": [
        2,
        8
      ],
      "hint": "This means something like 8 piles of 2 cookies.",
      "answer": 16,
      "formulaOperation": "multiplication",
      "formulaOrientation": "vertical",
      "type": "number"
    },
    {
      "id": 8,
      "formulaNumbers": [
        2,
        9
      ],
      "hint": "This means something like 9 piles of 2 cookies.",
      "answer": 18,
      "formulaOperation": "multiplication",
      "formulaOrientation": "vertical",
      "type": "number"
    }
  ]
}
